{
    "output": {
        "blocklist": [],
        "equalizer#0": {
            "balance": 0.0,
            "bypass": false,
            "input-gain": -7.3,
            "left": {
                "band0": {
                    "frequency": 16.0,
                    "gain": 6.3,
                    "mode": "APO (DR)",
                    "mute": false,
                    "q": 0.38,
                    "slope": "x1",
                    "solo": false,
                    "type": "Bell",
                    "width": 4.0
                },
                "band1": {
                    "frequency": 312.0,
                    "gain": -4.4,
                    "mode": "APO (DR)",
                    "mute": false,
                    "q": 0.36,
                    "slope": "x1",
                    "solo": false,
                    "type": "Bell",
                    "width": 4.0
                },
                "band2": {
                    "frequency": 1323.0,
                    "gain": -3.8,
                    "mode": "APO (DR)",
                    "mute": false,
                    "q": 1.85,
                    "slope": "x1",
                    "solo": false,
                    "type": "Bell",
                    "width": 4.0
                },
                "band3": {
                    "frequency": 2825.0,
                    "gain": 7.4,
                    "mode": "APO (DR)",
                    "mute": false,
                    "q": 1.13,
                    "slope": "x1",
                    "solo": false,
                    "type": "Bell",
                    "width": 4.0
                },
                "band4": {
                    "frequency": 17172.0,
                    "gain": 6.9,
                    "mode": "APO (DR)",
                    "mute": false,
                    "q": 0.42,
                    "slope": "x1",
                    "solo": false,
                    "type": "Bell",
                    "width": 4.0
                },
                "band5": {
                    "frequency": 3049.0,
                    "gain": -1.4,
                    "mode": "APO (DR)",
                    "mute": false,
                    "q": 4.14,
                    "slope": "x1",
                    "solo": false,
                    "type": "Bell",
                    "width": 4.0
                },
                "band6": {
                    "frequency": 4422.0,
                    "gain": 2.8,
                    "mode": "APO (DR)",
                    "mute": false,
                    "q": 2.44,
                    "slope": "x1",
                    "solo": false,
                    "type": "Bell",
                    "width": 4.0
                },
                "band7": {
                    "frequency": 6461.0,
                    "gain": -6.2,
                    "mode": "APO (DR)",
                    "mute": false,
                    "q": 3.97,
                    "slope": "x1",
                    "solo": false,
                    "type": "Bell",
                    "width": 4.0
                },
                "band8": {
                    "frequency": 11439.0,
                    "gain": 1.6,
                    "mode": "APO (DR)",
                    "mute": false,
                    "q": 1.73,
                    "slope": "x1",
                    "solo": false,
                    "type": "Bell",
                    "width": 4.0
                },
                "band9": {
                    "frequency": 20846.0,
                    "gain": 1.1,
                    "mode": "APO (DR)",
                    "mute": false,
                    "q": 2.92,
                    "slope": "x1",
                    "solo": false,
                    "type": "Bell",
                    "width": 4.0
                }
            },
            "mode": "IIR",
            "num-bands": 10,
            "output-gain": 7.3,
            "pitch-left": 0.0,
            "pitch-right": 0.0,
            "right": {
                "band0": {
                    "frequency": 16.0,
                    "gain": 6.3,
                    "mode": "APO (DR)",
                    "mute": false,
                    "q": 0.38,
                    "slope": "x1",
                    "solo": false,
                    "type": "Bell",
                    "width": 4.0
                },
                "band1": {
                    "frequency": 312.0,
                    "gain": -4.4,
                    "mode": "APO (DR)",
                    "mute": false,
                    "q": 0.36,
                    "slope": "x1",
                    "solo": false,
                    "type": "Bell",
                    "width": 4.0
                },
                "band2": {
                    "frequency": 1323.0,
                    "gain": -3.8,
                    "mode": "APO (DR)",
                    "mute": false,
                    "q": 1.85,
                    "slope": "x1",
                    "solo": false,
                    "type": "Bell",
                    "width": 4.0
                },
                "band3": {
                    "frequency": 2825.0,
                    "gain": 7.4,
                    "mode": "APO (DR)",
                    "mute": false,
                    "q": 1.13,
                    "slope": "x1",
                    "solo": false,
                    "type": "Bell",
                    "width": 4.0
                },
                "band4": {
                    "frequency": 17172.0,
                    "gain": 6.9,
                    "mode": "APO (DR)",
                    "mute": false,
                    "q": 0.42,
                    "slope": "x1",
                    "solo": false,
                    "type": "Bell",
                    "width": 4.0
                },
                "band5": {
                    "frequency": 3049.0,
                    "gain": -1.4,
                    "mode": "APO (DR)",
                    "mute": false,
                    "q": 4.14,
                    "slope": "x1",
                    "solo": false,
                    "type": "Bell",
                    "width": 4.0
                },
                "band6": {
                    "frequency": 4422.0,
                    "gain": 2.8,
                    "mode": "APO (DR)",
                    "mute": false,
                    "q": 2.44,
                    "slope": "x1",
                    "solo": false,
                    "type": "Bell",
                    "width": 4.0
                },
                "band7": {
                    "frequency": 6461.0,
                    "gain": -6.2,
                    "mode": "APO (DR)",
                    "mute": false,
                    "q": 3.97,
                    "slope": "x1",
                    "solo": false,
                    "type": "Bell",
                    "width": 4.0
                },
                "band8": {
                    "frequency": 11439.0,
                    "gain": 1.6,
                    "mode": "APO (DR)",
                    "mute": false,
                    "q": 1.73,
                    "slope": "x1",
                    "solo": false,
                    "type": "Bell",
                    "width": 4.0
                },
                "band9": {
                    "frequency": 20846.0,
                    "gain": 1.1,
                    "mode": "APO (DR)",
                    "mute": false,
                    "q": 2.92,
                    "slope": "x1",
                    "solo": false,
                    "type": "Bell",
                    "width": 4.0
                }
            },
            "split-channels": false
        },
        "plugins_order": [
            "equalizer#0"
        ]
    }
}