{
    "output": {
        "blocklist": [],
        "equalizer#0": {
            "balance": 0.0,
            "bypass": false,
            "input-gain": -6.7,
            "left": {
                "band0": {
                    "frequency": 22.0,
                    "gain": 6.0,
                    "mode": "APO (DR)",
                    "mute": false,
                    "q": 1.01,
                    "slope": "x1",
                    "solo": false,
                    "type": "Bell",
                    "width": 4.0
                },
                "band1": {
                    "frequency": 149.0,
                    "gain": -3.6,
                    "mode": "APO (DR)",
                    "mute": false,
                    "q": 1.44,
                    "slope": "x1",
                    "solo": false,
                    "type": "Bell",
                    "width": 4.0
                },
                "band2": {
                    "frequency": 2808.0,
                    "gain": -5.4,
                    "mode": "APO (DR)",
                    "mute": false,
                    "q": 1.58,
                    "slope": "x1",
                    "solo": false,
                    "type": "Bell",
                    "width": 4.0
                },
                "band3": {
                    "frequency": 5109.0,
                    "gain": 6.9,
                    "mode": "APO (DR)",
                    "mute": false,
                    "q": 1.56,
                    "slope": "x1",
                    "solo": false,
                    "type": "Bell",
                    "width": 4.0
                },
                "band4": {
                    "frequency": 17769.0,
                    "gain": 6.6,
                    "mode": "APO (DR)",
                    "mute": false,
                    "q": 0.37,
                    "slope": "x1",
                    "solo": false,
                    "type": "Bell",
                    "width": 4.0
                },
                "band5": {
                    "frequency": 611.0,
                    "gain": 1.6,
                    "mode": "APO (DR)",
                    "mute": false,
                    "q": 1.47,
                    "slope": "x1",
                    "solo": false,
                    "type": "Bell",
                    "width": 4.0
                },
                "band6": {
                    "frequency": 6529.0,
                    "gain": 1.9,
                    "mode": "APO (DR)",
                    "mute": false,
                    "q": 4.36,
                    "slope": "x1",
                    "solo": false,
                    "type": "Bell",
                    "width": 4.0
                },
                "band7": {
                    "frequency": 8300.0,
                    "gain": -1.2,
                    "mode": "APO (DR)",
                    "mute": false,
                    "q": 1.05,
                    "slope": "x1",
                    "solo": false,
                    "type": "Bell",
                    "width": 4.0
                },
                "band8": {
                    "frequency": 13460.0,
                    "gain": 1.4,
                    "mode": "APO (DR)",
                    "mute": false,
                    "q": 1.98,
                    "slope": "x1",
                    "solo": false,
                    "type": "Bell",
                    "width": 4.0
                },
                "band9": {
                    "frequency": 17413.0,
                    "gain": -0.8,
                    "mode": "APO (DR)",
                    "mute": false,
                    "q": 2.04,
                    "slope": "x1",
                    "solo": false,
                    "type": "Bell",
                    "width": 4.0
                },
                "band10": {
                    "frequency": 80.0,
                    "gain": 1.0,
                    "mode": "APO (DR)",
                    "mute": false,
                    "q": 0.45,
                    "slope": "x1",
                    "solo": false,
                    "type": "Bell",
                    "width": 4.0
                },
                "band11": {
                    "frequency": 110.0,
                    "gain": -5.8,
                    "mode": "APO (DR)",
                    "mute": false,
                    "q": 0.75,
                    "slope": "x1",
                    "solo": false,
                    "type": "Lo-shelf",
                    "width": 4.0
                },
                "band12": {
                    "frequency": 6000.0,
                    "gain": -1.2,
                    "mode": "APO (DR)",
                    "mute": false,
                    "q": 0.707,
                    "slope": "x1",
                    "solo": false,
                    "type": "Hi-shelf",
                    "width": 4.0
                },
                "band13": {
                    "frequency": 11000.0,
                    "gain": 0.8,
                    "mode": "APO (DR)",
                    "mute": false,
                    "q": 1.25,
                    "slope": "x1",
                    "solo": false,
                    "type": "Hi-shelf",
                    "width": 4.0
                }
            },
            "mode": "IIR",
            "num-bands": 14,
            "output-gain": 6.7,
            "pitch-left": 0.0,
            "pitch-right": 0.0,
            "right": {
                "band0": {
                    "frequency": 22.0,
                    "gain": 6.0,
                    "mode": "APO (DR)",
                    "mute": false,
                    "q": 1.01,
                    "slope": "x1",
                    "solo": false,
                    "type": "Bell",
                    "width": 4.0
                },
                "band1": {
                    "frequency": 149.0,
                    "gain": -3.6,
                    "mode": "APO (DR)",
                    "mute": false,
                    "q": 1.44,
                    "slope": "x1",
                    "solo": false,
                    "type": "Bell",
                    "width": 4.0
                },
                "band2": {
                    "frequency": 2808.0,
                    "gain": -5.4,
                    "mode": "APO (DR)",
                    "mute": false,
                    "q": 1.58,
                    "slope": "x1",
                    "solo": false,
                    "type": "Bell",
                    "width": 4.0
                },
                "band3": {
                    "frequency": 5109.0,
                    "gain": 6.9,
                    "mode": "APO (DR)",
                    "mute": false,
                    "q": 1.56,
                    "slope": "x1",
                    "solo": false,
                    "type": "Bell",
                    "width": 4.0
                },
                "band4": {
                    "frequency": 17769.0,
                    "gain": 6.6,
                    "mode": "APO (DR)",
                    "mute": false,
                    "q": 0.37,
                    "slope": "x1",
                    "solo": false,
                    "type": "Bell",
                    "width": 4.0
                },
                "band5": {
                    "frequency": 611.0,
                    "gain": 1.6,
                    "mode": "APO (DR)",
                    "mute": false,
                    "q": 1.47,
                    "slope": "x1",
                    "solo": false,
                    "type": "Bell",
                    "width": 4.0
                },
                "band6": {
                    "frequency": 6529.0,
                    "gain": 1.9,
                    "mode": "APO (DR)",
                    "mute": false,
                    "q": 4.36,
                    "slope": "x1",
                    "solo": false,
                    "type": "Bell",
                    "width": 4.0
                },
                "band7": {
                    "frequency": 8300.0,
                    "gain": -1.2,
                    "mode": "APO (DR)",
                    "mute": false,
                    "q": 1.05,
                    "slope": "x1",
                    "solo": false,
                    "type": "Bell",
                    "width": 4.0
                },
                "band8": {
                    "frequency": 13460.0,
                    "gain": 1.4,
                    "mode": "APO (DR)",
                    "mute": false,
                    "q": 1.98,
                    "slope": "x1",
                    "solo": false,
                    "type": "Bell",
                    "width": 4.0
                },
                "band9": {
                    "frequency": 17413.0,
                    "gain": -0.8,
                    "mode": "APO (DR)",
                    "mute": false,
                    "q": 2.04,
                    "slope": "x1",
                    "solo": false,
                    "type": "Bell",
                    "width": 4.0
                },
                "band10": {
                    "frequency": 80.0,
                    "gain": 1.0,
                    "mode": "APO (DR)",
                    "mute": false,
                    "q": 0.45,
                    "slope": "x1",
                    "solo": false,
                    "type": "Bell",
                    "width": 4.0
                },
                "band11": {
                    "frequency": 110.0,
                    "gain": -5.8,
                    "mode": "APO (DR)",
                    "mute": false,
                    "q": 0.75,
                    "slope": "x1",
                    "solo": false,
                    "type": "Lo-shelf",
                    "width": 4.0
                },
                "band12": {
                    "frequency": 6000.0,
                    "gain": -1.2,
                    "mode": "APO (DR)",
                    "mute": false,
                    "q": 0.707,
                    "slope": "x1",
                    "solo": false,
                    "type": "Hi-shelf",
                    "width": 4.0
                },
                "band13": {
                    "frequency": 11000.0,
                    "gain": 0.8,
                    "mode": "APO (DR)",
                    "mute": false,
                    "q": 1.25,
                    "slope": "x1",
                    "solo": false,
                    "type": "Hi-shelf",
                    "width": 4.0
                }
            },
            "split-channels": false
        },
        "plugins_order": [
            "equalizer#0"
        ]
    }
}