{
    "output": {
        "blocklist": [],
        "equalizer#0": {
            "balance": 0.0,
            "bypass": false,
            "input-gain": -7.5,
            "left": {
                "band0": {
                    "frequency": 17.0,
                    "gain": -10.0,
                    "mode": "APO (DR)",
                    "mute": false,
                    "q": 0.22,
                    "slope": "x1",
                    "solo": false,
                    "type": "Bell",
                    "width": 4.0
                },
                "band1": {
                    "frequency": 151.0,
                    "gain": -5.1,
                    "mode": "APO (DR)",
                    "mute": false,
                    "q": 0.34,
                    "slope": "x1",
                    "solo": false,
                    "type": "Bell",
                    "width": 4.0
                },
                "band2": {
                    "frequency": 886.0,
                    "gain": 5.4,
                    "mode": "APO (DR)",
                    "mute": false,
                    "q": 0.9,
                    "slope": "x1",
                    "solo": false,
                    "type": "Bell",
                    "width": 4.0
                },
                "band3": {
                    "frequency": 2168.0,
                    "gain": 3.2,
                    "mode": "APO (DR)",
                    "mute": false,
                    "q": 2.07,
                    "slope": "x1",
                    "solo": false,
                    "type": "Bell",
                    "width": 4.0
                },
                "band4": {
                    "frequency": 13239.0,
                    "gain": 7.1,
                    "mode": "APO (DR)",
                    "mute": false,
                    "q": 0.79,
                    "slope": "x1",
                    "solo": false,
                    "type": "Bell",
                    "width": 4.0
                },
                "band5": {
                    "frequency": 490.0,
                    "gain": 0.3,
                    "mode": "APO (DR)",
                    "mute": false,
                    "q": 3.28,
                    "slope": "x1",
                    "solo": false,
                    "type": "Bell",
                    "width": 4.0
                },
                "band6": {
                    "frequency": 3514.0,
                    "gain": 1.4,
                    "mode": "APO (DR)",
                    "mute": false,
                    "q": 1.96,
                    "slope": "x1",
                    "solo": false,
                    "type": "Bell",
                    "width": 4.0
                },
                "band7": {
                    "frequency": 5534.0,
                    "gain": -6.5,
                    "mode": "APO (DR)",
                    "mute": false,
                    "q": 2.65,
                    "slope": "x1",
                    "solo": false,
                    "type": "Bell",
                    "width": 4.0
                },
                "band8": {
                    "frequency": 8370.0,
                    "gain": 3.7,
                    "mode": "APO (DR)",
                    "mute": false,
                    "q": 2.52,
                    "slope": "x1",
                    "solo": false,
                    "type": "Bell",
                    "width": 4.0
                },
                "band9": {
                    "frequency": 19735.0,
                    "gain": -2.5,
                    "mode": "APO (DR)",
                    "mute": false,
                    "q": 2.79,
                    "slope": "x1",
                    "solo": false,
                    "type": "Bell",
                    "width": 4.0
                }
            },
            "mode": "IIR",
            "num-bands": 10,
            "output-gain": 7.5,
            "pitch-left": 0.0,
            "pitch-right": 0.0,
            "right": {
                "band0": {
                    "frequency": 17.0,
                    "gain": -10.0,
                    "mode": "APO (DR)",
                    "mute": false,
                    "q": 0.22,
                    "slope": "x1",
                    "solo": false,
                    "type": "Bell",
                    "width": 4.0
                },
                "band1": {
                    "frequency": 151.0,
                    "gain": -5.1,
                    "mode": "APO (DR)",
                    "mute": false,
                    "q": 0.34,
                    "slope": "x1",
                    "solo": false,
                    "type": "Bell",
                    "width": 4.0
                },
                "band2": {
                    "frequency": 886.0,
                    "gain": 5.4,
                    "mode": "APO (DR)",
                    "mute": false,
                    "q": 0.9,
                    "slope": "x1",
                    "solo": false,
                    "type": "Bell",
                    "width": 4.0
                },
                "band3": {
                    "frequency": 2168.0,
                    "gain": 3.2,
                    "mode": "APO (DR)",
                    "mute": false,
                    "q": 2.07,
                    "slope": "x1",
                    "solo": false,
                    "type": "Bell",
                    "width": 4.0
                },
                "band4": {
                    "frequency": 13239.0,
                    "gain": 7.1,
                    "mode": "APO (DR)",
                    "mute": false,
                    "q": 0.79,
                    "slope": "x1",
                    "solo": false,
                    "type": "Bell",
                    "width": 4.0
                },
                "band5": {
                    "frequency": 490.0,
                    "gain": 0.3,
                    "mode": "APO (DR)",
                    "mute": false,
                    "q": 3.28,
                    "slope": "x1",
                    "solo": false,
                    "type": "Bell",
                    "width": 4.0
                },
                "band6": {
                    "frequency": 3514.0,
                    "gain": 1.4,
                    "mode": "APO (DR)",
                    "mute": false,
                    "q": 1.96,
                    "slope": "x1",
                    "solo": false,
                    "type": "Bell",
                    "width": 4.0
                },
                "band7": {
                    "frequency": 5534.0,
                    "gain": -6.5,
                    "mode": "APO (DR)",
                    "mute": false,
                    "q": 2.65,
                    "slope": "x1",
                    "solo": false,
                    "type": "Bell",
                    "width": 4.0
                },
                "band8": {
                    "frequency": 8370.0,
                    "gain": 3.7,
                    "mode": "APO (DR)",
                    "mute": false,
                    "q": 2.52,
                    "slope": "x1",
                    "solo": false,
                    "type": "Bell",
                    "width": 4.0
                },
                "band9": {
                    "frequency": 19735.0,
                    "gain": -2.5,
                    "mode": "APO (DR)",
                    "mute": false,
                    "q": 2.79,
                    "slope": "x1",
                    "solo": false,
                    "type": "Bell",
                    "width": 4.0
                }
            },
            "split-channels": false
        },
        "plugins_order": [
            "equalizer#0"
        ]
    }
}