{
    "output": {
        "blocklist": [],
        "equalizer#0": {
            "balance": 0.0,
            "bypass": false,
            "input-gain": -6.3,
            "left": {
                "band0": {
                    "frequency": 24.0,
                    "gain": 6.2,
                    "mode": "APO (DR)",
                    "mute": false,
                    "q": 0.44,
                    "slope": "x1",
                    "solo": false,
                    "type": "Bell",
                    "width": 4.0
                },
                "band1": {
                    "frequency": 163.0,
                    "gain": -2.4,
                    "mode": "APO (DR)",
                    "mute": false,
                    "q": 1.0,
                    "slope": "x1",
                    "solo": false,
                    "type": "Bell",
                    "width": 4.0
                },
                "band2": {
                    "frequency": 3852.0,
                    "gain": -2.8,
                    "mode": "APO (DR)",
                    "mute": false,
                    "q": 1.19,
                    "slope": "x1",
                    "solo": false,
                    "type": "Bell",
                    "width": 4.0
                },
                "band3": {
                    "frequency": 4147.0,
                    "gain": 3.8,
                    "mode": "APO (DR)",
                    "mute": false,
                    "q": 5.58,
                    "slope": "x1",
                    "solo": false,
                    "type": "Bell",
                    "width": 4.0
                },
                "band4": {
                    "frequency": 8386.0,
                    "gain": 4.9,
                    "mode": "APO (DR)",
                    "mute": false,
                    "q": 1.55,
                    "slope": "x1",
                    "solo": false,
                    "type": "Bell",
                    "width": 4.0
                },
                "band5": {
                    "frequency": 779.0,
                    "gain": 0.9,
                    "mode": "APO (DR)",
                    "mute": false,
                    "q": 3.48,
                    "slope": "x1",
                    "solo": false,
                    "type": "Bell",
                    "width": 4.0
                },
                "band6": {
                    "frequency": 1388.0,
                    "gain": -0.9,
                    "mode": "APO (DR)",
                    "mute": false,
                    "q": 5.73,
                    "slope": "x1",
                    "solo": false,
                    "type": "Bell",
                    "width": 4.0
                },
                "band7": {
                    "frequency": 6418.0,
                    "gain": 0.9,
                    "mode": "APO (DR)",
                    "mute": false,
                    "q": 5.41,
                    "slope": "x1",
                    "solo": false,
                    "type": "Bell",
                    "width": 4.0
                },
                "band8": {
                    "frequency": 11987.0,
                    "gain": 2.3,
                    "mode": "APO (DR)",
                    "mute": false,
                    "q": 1.65,
                    "slope": "x1",
                    "solo": false,
                    "type": "Bell",
                    "width": 4.0
                },
                "band9": {
                    "frequency": 19904.0,
                    "gain": -9.2,
                    "mode": "APO (DR)",
                    "mute": false,
                    "q": 0.45,
                    "slope": "x1",
                    "solo": false,
                    "type": "Bell",
                    "width": 4.0
                }
            },
            "mode": "IIR",
            "num-bands": 10,
            "output-gain": 6.3,
            "pitch-left": 0.0,
            "pitch-right": 0.0,
            "right": {
                "band0": {
                    "frequency": 24.0,
                    "gain": 6.2,
                    "mode": "APO (DR)",
                    "mute": false,
                    "q": 0.44,
                    "slope": "x1",
                    "solo": false,
                    "type": "Bell",
                    "width": 4.0
                },
                "band1": {
                    "frequency": 163.0,
                    "gain": -2.4,
                    "mode": "APO (DR)",
                    "mute": false,
                    "q": 1.0,
                    "slope": "x1",
                    "solo": false,
                    "type": "Bell",
                    "width": 4.0
                },
                "band2": {
                    "frequency": 3852.0,
                    "gain": -2.8,
                    "mode": "APO (DR)",
                    "mute": false,
                    "q": 1.19,
                    "slope": "x1",
                    "solo": false,
                    "type": "Bell",
                    "width": 4.0
                },
                "band3": {
                    "frequency": 4147.0,
                    "gain": 3.8,
                    "mode": "APO (DR)",
                    "mute": false,
                    "q": 5.58,
                    "slope": "x1",
                    "solo": false,
                    "type": "Bell",
                    "width": 4.0
                },
                "band4": {
                    "frequency": 8386.0,
                    "gain": 4.9,
                    "mode": "APO (DR)",
                    "mute": false,
                    "q": 1.55,
                    "slope": "x1",
                    "solo": false,
                    "type": "Bell",
                    "width": 4.0
                },
                "band5": {
                    "frequency": 779.0,
                    "gain": 0.9,
                    "mode": "APO (DR)",
                    "mute": false,
                    "q": 3.48,
                    "slope": "x1",
                    "solo": false,
                    "type": "Bell",
                    "width": 4.0
                },
                "band6": {
                    "frequency": 1388.0,
                    "gain": -0.9,
                    "mode": "APO (DR)",
                    "mute": false,
                    "q": 5.73,
                    "slope": "x1",
                    "solo": false,
                    "type": "Bell",
                    "width": 4.0
                },
                "band7": {
                    "frequency": 6418.0,
                    "gain": 0.9,
                    "mode": "APO (DR)",
                    "mute": false,
                    "q": 5.41,
                    "slope": "x1",
                    "solo": false,
                    "type": "Bell",
                    "width": 4.0
                },
                "band8": {
                    "frequency": 11987.0,
                    "gain": 2.3,
                    "mode": "APO (DR)",
                    "mute": false,
                    "q": 1.65,
                    "slope": "x1",
                    "solo": false,
                    "type": "Bell",
                    "width": 4.0
                },
                "band9": {
                    "frequency": 19904.0,
                    "gain": -9.2,
                    "mode": "APO (DR)",
                    "mute": false,
                    "q": 0.45,
                    "slope": "x1",
                    "solo": false,
                    "type": "Bell",
                    "width": 4.0
                }
            },
            "split-channels": false
        },
        "plugins_order": [
            "equalizer#0"
        ]
    }
}