{
    "output": {
        "blocklist": [],
        "equalizer#0": {
            "balance": 0.0,
            "bypass": false,
            "input-gain": -5.9,
            "left": {
                "band0": {
                    "frequency": 27.0,
                    "gain": -9.7,
                    "mode": "APO (DR)",
                    "mute": false,
                    "q": 0.43,
                    "slope": "x1",
                    "solo": false,
                    "type": "Bell",
                    "width": 4.0
                },
                "band1": {
                    "frequency": 901.0,
                    "gain": 3.7,
                    "mode": "APO (DR)",
                    "mute": false,
                    "q": 2.67,
                    "slope": "x1",
                    "solo": false,
                    "type": "Bell",
                    "width": 4.0
                },
                "band2": {
                    "frequency": 1899.0,
                    "gain": 4.4,
                    "mode": "APO (DR)",
                    "mute": false,
                    "q": 1.62,
                    "slope": "x1",
                    "solo": false,
                    "type": "Bell",
                    "width": 4.0
                },
                "band3": {
                    "frequency": 4313.0,
                    "gain": 8.1,
                    "mode": "APO (DR)",
                    "mute": false,
                    "q": 1.97,
                    "slope": "x1",
                    "solo": false,
                    "type": "Bell",
                    "width": 4.0
                },
                "band4": {
                    "frequency": 8731.0,
                    "gain": -8.5,
                    "mode": "APO (DR)",
                    "mute": false,
                    "q": 0.7,
                    "slope": "x1",
                    "solo": false,
                    "type": "Bell",
                    "width": 4.0
                },
                "band5": {
                    "frequency": 324.0,
                    "gain": -1.3,
                    "mode": "APO (DR)",
                    "mute": false,
                    "q": 1.27,
                    "slope": "x1",
                    "solo": false,
                    "type": "Bell",
                    "width": 4.0
                },
                "band6": {
                    "frequency": 6658.0,
                    "gain": -1.4,
                    "mode": "APO (DR)",
                    "mute": false,
                    "q": 4.42,
                    "slope": "x1",
                    "solo": false,
                    "type": "Bell",
                    "width": 4.0
                },
                "band7": {
                    "frequency": 12779.0,
                    "gain": -3.2,
                    "mode": "APO (DR)",
                    "mute": false,
                    "q": 1.27,
                    "slope": "x1",
                    "solo": false,
                    "type": "Bell",
                    "width": 4.0
                },
                "band8": {
                    "frequency": 16194.0,
                    "gain": -2.1,
                    "mode": "APO (DR)",
                    "mute": false,
                    "q": 1.21,
                    "slope": "x1",
                    "solo": false,
                    "type": "Bell",
                    "width": 4.0
                },
                "band9": {
                    "frequency": 19108.0,
                    "gain": 4.4,
                    "mode": "APO (DR)",
                    "mute": false,
                    "q": 0.19,
                    "slope": "x1",
                    "solo": false,
                    "type": "Bell",
                    "width": 4.0
                }
            },
            "mode": "IIR",
            "num-bands": 10,
            "output-gain": 5.9,
            "pitch-left": 0.0,
            "pitch-right": 0.0,
            "right": {
                "band0": {
                    "frequency": 27.0,
                    "gain": -9.7,
                    "mode": "APO (DR)",
                    "mute": false,
                    "q": 0.43,
                    "slope": "x1",
                    "solo": false,
                    "type": "Bell",
                    "width": 4.0
                },
                "band1": {
                    "frequency": 901.0,
                    "gain": 3.7,
                    "mode": "APO (DR)",
                    "mute": false,
                    "q": 2.67,
                    "slope": "x1",
                    "solo": false,
                    "type": "Bell",
                    "width": 4.0
                },
                "band2": {
                    "frequency": 1899.0,
                    "gain": 4.4,
                    "mode": "APO (DR)",
                    "mute": false,
                    "q": 1.62,
                    "slope": "x1",
                    "solo": false,
                    "type": "Bell",
                    "width": 4.0
                },
                "band3": {
                    "frequency": 4313.0,
                    "gain": 8.1,
                    "mode": "APO (DR)",
                    "mute": false,
                    "q": 1.97,
                    "slope": "x1",
                    "solo": false,
                    "type": "Bell",
                    "width": 4.0
                },
                "band4": {
                    "frequency": 8731.0,
                    "gain": -8.5,
                    "mode": "APO (DR)",
                    "mute": false,
                    "q": 0.7,
                    "slope": "x1",
                    "solo": false,
                    "type": "Bell",
                    "width": 4.0
                },
                "band5": {
                    "frequency": 324.0,
                    "gain": -1.3,
                    "mode": "APO (DR)",
                    "mute": false,
                    "q": 1.27,
                    "slope": "x1",
                    "solo": false,
                    "type": "Bell",
                    "width": 4.0
                },
                "band6": {
                    "frequency": 6658.0,
                    "gain": -1.4,
                    "mode": "APO (DR)",
                    "mute": false,
                    "q": 4.42,
                    "slope": "x1",
                    "solo": false,
                    "type": "Bell",
                    "width": 4.0
                },
                "band7": {
                    "frequency": 12779.0,
                    "gain": -3.2,
                    "mode": "APO (DR)",
                    "mute": false,
                    "q": 1.27,
                    "slope": "x1",
                    "solo": false,
                    "type": "Bell",
                    "width": 4.0
                },
                "band8": {
                    "frequency": 16194.0,
                    "gain": -2.1,
                    "mode": "APO (DR)",
                    "mute": false,
                    "q": 1.21,
                    "slope": "x1",
                    "solo": false,
                    "type": "Bell",
                    "width": 4.0
                },
                "band9": {
                    "frequency": 19108.0,
                    "gain": 4.4,
                    "mode": "APO (DR)",
                    "mute": false,
                    "q": 0.19,
                    "slope": "x1",
                    "solo": false,
                    "type": "Bell",
                    "width": 4.0
                }
            },
            "split-channels": false
        },
        "plugins_order": [
            "equalizer#0"
        ]
    }
}